litestar_tailwind_cli/__about__.py
litestar_tailwind_cli/__init__.py
litestar_tailwind_cli/cli.py
litestar_tailwind_cli/utils.py
litestar_tailwind-0.2.3.dist-info/METADATA
litestar_tailwind-0.2.3.dist-info/WHEEL
litestar_tailwind-0.2.3.dist-info/licenses/LICENSE.txt
litestar_tailwind-0.2.3.dist-info/RECORD
