Metadata-Version: 2.4
Name: litestar-tailwind
Version: 0.2.3
Summary: Provides a CLI plugin for Litestar to use Tailwind CSS via the Tailwind CLI.
Project-URL: Documentation, https://github.com/aoi-cistus/litestar-tailwind#readme
Project-URL: Issues, https://github.com/aoi-cistus/litestar-tailwind/issues
Project-URL: Source, https://github.com/aoi-cistus/litestar-tailwind
Author-email: Tobi DEGNON <tobidegnon@proton.me>
Maintainer-email: Aoi <aoicistus@gmail.com>
License-Expression: MIT
License-File: LICENSE.txt
Keywords: litestar,tailwindcss
Classifier: Development Status :: 4 - Beta
Classifier: Intended Audience :: Developers
Classifier: Programming Language :: Python
Classifier: Programming Language :: Python :: 3 :: Only
Classifier: Programming Language :: Python :: 3.10
Classifier: Programming Language :: Python :: 3.11
Classifier: Programming Language :: Python :: 3.12
Classifier: Programming Language :: Python :: 3.13
Classifier: Programming Language :: Python :: Implementation :: CPython
Classifier: Programming Language :: Python :: Implementation :: PyPy
Classifier: Topic :: Software Development
Classifier: Typing :: Typed
Requires-Python: >=3.10
Requires-Dist: litestar[standard]
